pathpilot/__init__.py
pathpilot/_file/__init__.py
pathpilot/_file/_csv.py
pathpilot/_file/_excel.py
pathpilot/_file/_pickle.py
pathpilot/_file/_sqlite.py
pathpilot/_file/_text.py
pathpilot/_file/_zip.py
pathpilot/_file/base.py
pathpilot/_file/utils.py
pathpilot/_folder/__init__.py
pathpilot/_folder/backup.py
pathpilot/_folder/base.py
pathpilot/_folder/utils.py
pathpilot/core.py
pathpilot/decorators.py
pathpilot/exceptions.py
pathpilot/utils.py
pathpilot-0.3.5.dist-info/LICENSE
pathpilot-0.3.5.dist-info/METADATA
pathpilot-0.3.5.dist-info/WHEEL
pathpilot-0.3.5.dist-info/RECORD
