Metadata-Version: 2.1
Name: pathpilot
Version: 0.3.5
Summary: Library that facilitates file and folder manipulation in Python.
Home-page: https://github.com/zteinck/pathpilot
License: MIT
Author: Zachary Einck
Author-email: zacharyeinck@gmail.com
Requires-Python: >=3.8,<4.0
Classifier: License :: OSI Approved :: MIT License
Classifier: Programming Language :: Python :: 3
Classifier: Programming Language :: Python :: 3.8
Classifier: Programming Language :: Python :: 3.9
Classifier: Programming Language :: Python :: 3.10
Classifier: Programming Language :: Python :: 3.11
Classifier: Programming Language :: Python :: 3.12
Requires-Dist: XlsxWriter
Requires-Dist: cachegrab (>=0.2.2)
Requires-Dist: clockwork (>=0.4.0)
Requires-Dist: numpy
Requires-Dist: oddments (>=0.4.1)
Requires-Dist: pandas
Project-URL: Repository, https://github.com/zteinck/pathpilot
